napari_quoll/__init__.py
napari_quoll/_widget.py
napari_quoll/napari.yaml
napari_quoll/_tests/__init__.py
napari_quoll/_tests/test_widget.py
napari_quoll-0.0.1.dist-info/LICENSE
napari_quoll-0.0.1.dist-info/METADATA
napari_quoll-0.0.1.dist-info/WHEEL
napari_quoll-0.0.1.dist-info/entry_points.txt
napari_quoll-0.0.1.dist-info/top_level.txt
napari_quoll-0.0.1.dist-info/RECORD
