Metadata-Version: 2.1
Name: napari-quoll
Version: 0.0.1
Summary: Resolution estimation for electron tomography
Home-page: https://github.com/rosalindfranklininstitute/napari-quoll
Author: Elaine Ho
Author-email: Elaine.Ho@rfi.ac.uk
License: Apache-2.0
Project-URL: Bug Tracker, https://github.com/rosalindfranklininstitute/napari-quoll/issues
Project-URL: Documentation, https://github.com/rosalindfranklininstitute/napari-quoll#README.md
Project-URL: Source Code, https://github.com/rosalindfranklininstitute/napari-quoll
Project-URL: User Support, https://github.com/rosalindfranklininstitute/napari-quoll/issues
Classifier: Development Status :: 2 - Pre-Alpha
Classifier: Framework :: napari
Classifier: Intended Audience :: Developers
Classifier: License :: OSI Approved :: Apache Software License
Classifier: Operating System :: OS Independent
Classifier: Programming Language :: Python
Classifier: Programming Language :: Python :: 3
Classifier: Programming Language :: Python :: 3 :: Only
Classifier: Programming Language :: Python :: 3.8
Classifier: Programming Language :: Python :: 3.9
Classifier: Programming Language :: Python :: 3.10
Classifier: Topic :: Scientific/Engineering :: Image Processing
Requires-Python: >=3.7
License-File: LICENSE
Requires-Dist: numpy
Requires-Dist: magicgui
Requires-Dist: qtpy
Requires-Dist: quoll
Provides-Extra: testing
Requires-Dist: tox ; extra == 'testing'
Requires-Dist: pytest ; extra == 'testing'
Requires-Dist: pytest-cov ; extra == 'testing'
Requires-Dist: pytest-qt ; extra == 'testing'
Requires-Dist: napari ; extra == 'testing'
Requires-Dist: pyqt5 ; extra == 'testing'
